jupyter_tiktok/__init__.py
jupyter_tiktok/_version.py
jupyter_tiktok/handlers.py
jupyter_tiktok/tests/__init__.py
jupyter_tiktok/tests/test_handlers.py
jupyter_tiktok-0.0.2.data/data/etc/jupyter/jupyter_notebook_config.d/jupyter_tiktok.json
jupyter_tiktok-0.0.2.data/data/etc/jupyter/jupyter_server_config.d/jupyter_tiktok.json
jupyter_tiktok-0.0.2.data/data/share/jupyter/labextensions/@datalayer/jupyter-tiktok/build_log.json
jupyter_tiktok-0.0.2.data/data/share/jupyter/labextensions/@datalayer/jupyter-tiktok/package.json
jupyter_tiktok-0.0.2.data/data/share/jupyter/labextensions/@datalayer/jupyter-tiktok/schemas/@datalayer/jupyter-tiktok/package.json.orig
jupyter_tiktok-0.0.2.data/data/share/jupyter/labextensions/@datalayer/jupyter-tiktok/schemas/@datalayer/jupyter-tiktok/plugin.json
jupyter_tiktok-0.0.2.data/data/share/jupyter/labextensions/@datalayer/jupyter-tiktok/static/design_icons_lib_index_js.1280cdcae57d330ff882.js
jupyter_tiktok-0.0.2.data/data/share/jupyter/labextensions/@datalayer/jupyter-tiktok/static/design_icons_lib_index_js.1280cdcae57d330ff882.js.map
jupyter_tiktok-0.0.2.data/data/share/jupyter/labextensions/@datalayer/jupyter-tiktok/static/lib_index_js.9cc746dce8712e72831c.js
jupyter_tiktok-0.0.2.data/data/share/jupyter/labextensions/@datalayer/jupyter-tiktok/static/lib_index_js.9cc746dce8712e72831c.js.map
jupyter_tiktok-0.0.2.data/data/share/jupyter/labextensions/@datalayer/jupyter-tiktok/static/remoteEntry.4a3bdcb79d4fe4b70e1b.js
jupyter_tiktok-0.0.2.data/data/share/jupyter/labextensions/@datalayer/jupyter-tiktok/static/remoteEntry.4a3bdcb79d4fe4b70e1b.js.map
jupyter_tiktok-0.0.2.data/data/share/jupyter/labextensions/@datalayer/jupyter-tiktok/static/style.js
jupyter_tiktok-0.0.2.data/data/share/jupyter/labextensions/@datalayer/jupyter-tiktok/static/style_index_js.1421ddd705fe76f1ab56.js
jupyter_tiktok-0.0.2.data/data/share/jupyter/labextensions/@datalayer/jupyter-tiktok/static/style_index_js.1421ddd705fe76f1ab56.js.map
jupyter_tiktok-0.0.2.dist-info/METADATA
jupyter_tiktok-0.0.2.dist-info/WHEEL
jupyter_tiktok-0.0.2.dist-info/licenses/LICENSE
jupyter_tiktok-0.0.2.dist-info/RECORD
